behaverse/__init__.py
behaverse/conftest.py
behaverse/data/__init__.py
behaverse/data/dataset.py
behaverse/data/dataset_description.py
behaverse/data/dataset_test.py
behaverse/data/dvc_storage.py
behaverse/data/dvc_storage_test.py
behaverse/data/functional.py
behaverse/data/functions_test.py
behaverse/data/http_storage.py
behaverse/data/utils.py
behaverse/data/additional_storage/huggingface.py
behaverse/data/additional_storage/osf.py
behaverse/data/additional_storage/ulhpc.py
behaverse/data/additional_storage/zenodo.py
behaverse_data_loader-0.0.9.dev4.dist-info/licenses/LICENSE
behaverse_data_loader-0.0.9.dev4.dist-info/WHEEL
behaverse_data_loader-0.0.9.dev4.dist-info/METADATA
behaverse_data_loader-0.0.9.dev4.dist-info/RECORD
