Metadata-Version: 2.4
Name: behaverse-data-loader
Version: 0.0.9.dev4
Summary: Behaverse package.
Author-email: xCIT Development Team <contact@xcit.org>
Maintainer-email: Morteza Ansarinia <ansarinia@me.com>, Hoorieh Afkari <hoorieh.afkari@uni.lu>, Pedro Cardoso-Leite <pedro.cardosoleite@uni.lu>
Requires-Python: >=3.10
Classifier: Development Status :: 1 - Planning
Classifier: Intended Audience :: Developers
Classifier: Intended Audience :: Science/Research
Classifier: License :: OSI Approved :: MIT License
Classifier: Programming Language :: Python :: 3 :: Only
Classifier: Programming Language :: Python :: 3.10
Classifier: Programming Language :: Python :: 3.11
Classifier: Programming Language :: Python :: 3.12
Classifier: Topic :: Scientific/Engineering
License-File: LICENSE
Requires-Dist: pandas
Requires-Dist: tqdm
Requires-Dist: requests
Requires-Dist: dvc>3 ; extra == "dvc"
Requires-Dist: dvc-ssh ; extra == "dvc"
Requires-Dist: pytest ; extra == "test"
Project-URL: Documentation, https://behaverse.org/data-loader
Project-URL: Homepage, https://behaverse.org/data-loader
Project-URL: Repository, https://github.com/behaverse/data-loader
Provides-Extra: dvc
Provides-Extra: test
